thtml/__init__.py
thtml/__main__.py
thtml/body_fragment.py
thtml/cli.py
thtml/options.py
thtml/py.typed
thtml/types.py
thtml/scopes/__init__.py
thtml/scopes/document.html
thtml/scopes/fragment.html
thtml/scopes/py.typed
thtml/scopes/scope_html_parser.py
thtml/themes/__init__.py
thtml/themes/default.yml
thtml/themes/google-fonts.yml
thtml/themes/plain.yml
thtml/theming/__init__.py
thtml/theming/py.typed
thtml/theming/style_fragment.py
thtml/theming/theme.py
thtml/theming/theme_class.py
thtml/version/VERSION
thtml/version/__init__.py
thtml/version/py.typed
thtml-1.0.5.dist-info/LICENSE
thtml-1.0.5.dist-info/METADATA
thtml-1.0.5.dist-info/WHEEL
thtml-1.0.5.dist-info/entry_points.txt
thtml-1.0.5.dist-info/top_level.txt
thtml-1.0.5.dist-info/RECORD
