Metadata-Version: 2.1
Name: thtml
Version: 1.0.5
Summary: CLI tool for converting text to HTML
Home-page: https://github.com/cariad/thtml
Author: Cariad Eccleston
Author-email: cariad@cariad.io
License: MIT
Platform: UNKNOWN
Classifier: Development Status :: 5 - Production/Stable
Classifier: Environment :: Console
Classifier: License :: OSI Approved :: MIT License
Classifier: Natural Language :: English
Classifier: Operating System :: OS Independent
Classifier: Programming Language :: Python :: 3 :: Only
Classifier: Programming Language :: Python :: 3.8
Classifier: Programming Language :: Python :: 3.9
Classifier: Topic :: Utilities
Classifier: Typing :: Typed
Requires-Python: >=3.8
License-File: LICENSE
Requires-Dist: ansiscape (>=1.0.0)
Requires-Dist: naughtty (>=1.0.0)
Requires-Dist: pyyaml
